Pipfile
README.rst
requirements.txt
setup.cfg
setup.py
pynndb/__init__.py
pynndb/database.py
pynndb/index.py
pynndb/models.py
pynndb/mp.py
pynndb/replication.py
pynndb/table.py
pynndb/transaction.py
pynndb/types.py
pynndb/utils.py
pynndb.egg-info/PKG-INFO
pynndb.egg-info/SOURCES.txt
pynndb.egg-info/dependency_links.txt
pynndb.egg-info/requires.txt
pynndb.egg-info/top_level.txt