Metadata-Version: 1.1
Name: pynndb
Version: 1.1.5
Summary: Database library for Python based on LMDB storage engine
Home-page: https://github.com/oddjobz/pynndb
Author: Gareth Bult
Author-email: oddjobz@linux.co.uk
License: MIT
Keywords: pynndb,database,LMDB,python,ORM
Platform: UNKNOWN
Classifier: Development Status :: 4 - Beta
Classifier: Intended Audience :: Developers
Classifier: Topic :: Database :: Database Engines/Servers
Classifier: License :: OSI Approved :: MIT License
Classifier: Programming Language :: Python :: 3.6
